cocotbext/ahb/__init__.py
cocotbext/ahb/ahb_bus.py
cocotbext/ahb/ahb_master.py
cocotbext/ahb/ahb_monitor.py
cocotbext/ahb/ahb_slave.py
cocotbext/ahb/ahb_types.py
cocotbext/ahb/memory.py
cocotbext/ahb/sparse_memory.py
cocotbext/ahb/utils.py
cocotbext_ahb-0.5.1.dist-info/licenses/LICENSE
cocotbext_ahb-0.5.1.dist-info/METADATA
cocotbext_ahb-0.5.1.dist-info/WHEEL
cocotbext_ahb-0.5.1.dist-info/top_level.txt
cocotbext_ahb-0.5.1.dist-info/RECORD
