Metadata-Version: 2.4
Name: cocotbext-ahb
Version: 0.5.1
Summary: CocotbExt AHB Bus VIP
Author-email: Anderson Ignacio <anderson@aignacio.com>
License: MIT
Project-URL: Homepage, https://github.com/aignacio/cocotbext-ahb
Project-URL: Bug Tracker, https://github.com/aignacio/cocotbext-ahb/issues
Project-URL: Source Code, https://github.com/aignacio/cocotbext-ahb
Keywords: soc,vip,hdl,verilog,systemverilog,ahb
Classifier: Development Status :: 3 - Alpha
Classifier: Framework :: cocotb
Classifier: Intended Audience :: Developers
Classifier: License :: OSI Approved :: MIT License
Classifier: Operating System :: MacOS :: MacOS X
Classifier: Operating System :: Microsoft :: Windows
Classifier: Operating System :: Unix
Classifier: Programming Language :: Python :: 3
Classifier: Topic :: Scientific/Engineering :: Electronic Design Automation (EDA)
Requires-Python: >=3.6
License-File: LICENSE
Requires-Dist: cocotb>=1.8.0
Requires-Dist: cocotb-bus
Requires-Dist: packaging
Provides-Extra: test
Requires-Dist: cocotb>=2.0.0; extra == "test"
Dynamic: license-file
